protus/__init__.py
protus/protus.py
protus-0.1.0.dist-info/METADATA
protus-0.1.0.dist-info/WHEEL
protus-0.1.0.dist-info/top_level.txt
protus-0.1.0.dist-info/RECORD
