Metadata-Version: 2.1
Name: protus
Version: 0.1.0
Summary: Python SDK for Protus (https://protus.dev)
Home-page: https://protus.dev
Author: Tomer Gal
Author-email: tomer@protus.dev
Classifier: Programming Language :: Python :: 3
Classifier: License :: OSI Approved :: MIT License
Classifier: Operating System :: OS Independent
Requires-Python: >=3.12
